mail_utils/__init__.py
mail_utils/current_time.py
mail_utils/validate_mail.py
mail_utils/validate_number.py
mail_utils/write_file.py
Sendmails_messages-0.0.1.dist-info/METADATA
Sendmails_messages-0.0.1.dist-info/WHEEL
Sendmails_messages-0.0.1.dist-info/top_level.txt
Sendmails_messages-0.0.1.dist-info/RECORD
